Metadata-Version: 1.0
Name: cerca
Version: 0.3
Summary: A library and utility for scanning static websites for links
Home-page: https://github.com/dang3r/cerca
Author: Daniel Cardoza
Author-email: daniel@redbooth.com
License: MIT
Platform: UNKNOWN
